regressionTestSofiane/__init__.py
regressionTestSofiane/regressionTestSofiane.py
regressiontestsofiane-1.0.0.dist-info/licenses/LICENSE.txt
regressiontestsofiane-1.0.0.dist-info/METADATA
regressiontestsofiane-1.0.0.dist-info/WHEEL
regressiontestsofiane-1.0.0.dist-info/top_level.txt
regressiontestsofiane-1.0.0.dist-info/RECORD
