Metadata-Version: 2.4
Name: regressionTestSofiane
Version: 1.0.0
Summary: A simple linear regression implementation from scratch (by Sofiane)
Home-page: https://pypi.org/project/regressionTestSofiane/
Author: Bensetallah sofiane
Author-email: rtsof91@gmail.com
License: LICENSE.txt
License-File: LICENSE.txt
Requires-Dist: numpy
Dynamic: author
Dynamic: author-email
Dynamic: description
Dynamic: description-content-type
Dynamic: home-page
Dynamic: license
Dynamic: license-file
Dynamic: requires-dist
Dynamic: summary
